shapinteractions/__init__.py
shapinteractions/html_utils.py
shapinteractions/interactions.py
shapinteractions-0.1.dist-info/licenses/LICENSE
shapinteractions-0.1.dist-info/METADATA
shapinteractions-0.1.dist-info/WHEEL
shapinteractions-0.1.dist-info/top_level.txt
shapinteractions-0.1.dist-info/RECORD
