Metadata-Version: 2.4
Name: shapinteractions
Version: 0.1
Summary: Build a comprehensive interaction graph visualization
Home-page: https://github.com/fefurger/Interactions
Author: Felix Furger
Author-email: fefurger@hotmail.com
Classifier: Programming Language :: Python :: 3
Classifier: License :: OSI Approved :: GNU General Public License v3 (GPLv3)
Classifier: Operating System :: OS Independent
Requires-Python: >=3.8
License-File: LICENSE
Requires-Dist: matplotlib>=3.9.4
Requires-Dist: seaborn>=0.13.2
Requires-Dist: numpy>=2.0.2
Requires-Dist: pyvis>=0.3.2
Requires-Dist: scipy>=1.13.1
Requires-Dist: beautifulsoup4>=4.13.4
Dynamic: author
Dynamic: author-email
Dynamic: classifier
Dynamic: description
Dynamic: description-content-type
Dynamic: home-page
Dynamic: license-file
Dynamic: requires-dist
Dynamic: requires-python
Dynamic: summary
